topsis/__init__.py
topsis/topsis.py
topsis_himanshu_102303786-0.1.0.dist-info/licenses/LICENSE
topsis_himanshu_102303786-0.1.0.dist-info/METADATA
topsis_himanshu_102303786-0.1.0.dist-info/WHEEL
topsis_himanshu_102303786-0.1.0.dist-info/entry_points.txt
topsis_himanshu_102303786-0.1.0.dist-info/top_level.txt
topsis_himanshu_102303786-0.1.0.dist-info/RECORD
