Metadata-Version: 2.4
Name: Topsis-Himanshu-102303786
Version: 0.1.0
Summary: A Python package to solve Multi-Criteria Decision Making problems using TOPSIS.
Author: Himanshu Bansal
Author-email: himanshubansal162005@gmail.com
Requires-Python: >=3.7
License-File: LICENSE
Requires-Dist: pandas
Requires-Dist: numpy
Dynamic: author
Dynamic: author-email
Dynamic: description
Dynamic: description-content-type
Dynamic: license-file
Dynamic: requires-dist
Dynamic: requires-python
Dynamic: summary
